sed/__init__.py
sed/diagnostics.py
sed/binning/__init__.py
sed/binning/binning.py
sed/binning/numba_bin.py
sed/binning/utils.py
sed/calibrator/__init__.py
sed/calibrator/delay.py
sed/calibrator/energy.py
sed/calibrator/momentum.py
sed/config/NXmpes_config-HEXTOF.json
sed/config/NXmpes_config.json
sed/config/datasets.json
sed/config/default.yaml
sed/config/flash_example_config.yaml
sed/config/mpes_example_config.yaml
sed/config/sxp_example_config.yaml
sed/core/__init__.py
sed/core/config.py
sed/core/config_model.py
sed/core/dfops.py
sed/core/logging.py
sed/core/metadata.py
sed/core/processor.py
sed/dataset/__init__.py
sed/dataset/dataset.py
sed/io/__init__.py
sed/io/hdf5.py
sed/io/nexus.py
sed/io/tiff.py
sed/loader/__init__.py
sed/loader/loader_interface.py
sed/loader/mirrorutil.py
sed/loader/utils.py
sed/loader/base/__init__.py
sed/loader/base/loader.py
sed/loader/flash/__init__.py
sed/loader/flash/buffer_handler.py
sed/loader/flash/dataframe.py
sed/loader/flash/instruments.py
sed/loader/flash/loader.py
sed/loader/flash/metadata.py
sed/loader/flash/utils.py
sed/loader/generic/__init__.py
sed/loader/generic/loader.py
sed/loader/mpes/__init__.py
sed/loader/mpes/loader.py
sed/loader/mpes/metadata.py
sed/loader/sxp/__init__.py
sed/loader/sxp/loader.py
sed_processor-1.3.0.dist-info/licenses/LICENSE
sed_processor-1.3.0.dist-info/METADATA
sed_processor-1.3.0.dist-info/WHEEL
sed_processor-1.3.0.dist-info/top_level.txt
sed_processor-1.3.0.dist-info/RECORD
