Metadata-Version: 2.4
Name: sed-processor
Version: 1.3.0
Summary: Single Event Data Frame Processor: Backend to handle photoelectron resolved datastreams
Author-email: OpenCOMPES team <sed-processor@mpes.science>
License: MIT License
Project-URL: repository, https://github.com/OpenCOMPES/sed
Project-URL: documentation, https://opencompes.github.io/sed/
Keywords: sed,mpes,flash,arpes
Classifier: Programming Language :: Python :: 3.10
Classifier: Programming Language :: Python :: 3.11
Classifier: Programming Language :: Python :: 3.12
Classifier: Programming Language :: Python :: 3.13
Classifier: License :: OSI Approved :: MIT License
Classifier: Operating System :: OS Independent
Requires-Python: >=3.10
License-File: LICENSE
Requires-Dist: bokeh<3.7.0,>=2.4.2
Requires-Dist: dask<2024.8,>=2021.12.0
Requires-Dist: elabapi-python<5.2,>=5.0
Requires-Dist: fastdtw>=0.3.4
Requires-Dist: h5py>=3.6.0
Requires-Dist: ipympl>=0.9.1
Requires-Dist: ipywidgets>=8.1.5
Requires-Dist: lmfit>=1.0.3
Requires-Dist: matplotlib>=3.5.1
Requires-Dist: natsort>=8.1.0
Requires-Dist: numba>=0.55.1
Requires-Dist: numpy>=2.0.0
Requires-Dist: pandas>=1.4.1
Requires-Dist: photutils<2.0
Requires-Dist: psutil>=5.9.0
Requires-Dist: pynxtools-mpes>=0.2.6
Requires-Dist: pynxtools>=0.12.0
Requires-Dist: pyyaml>=6.0.0
Requires-Dist: scipy>=1.8.0
Requires-Dist: symmetrize>=0.5.5
Requires-Dist: threadpoolctl>=3.1.0
Requires-Dist: tifffile>=2022.2.9
Requires-Dist: tqdm>=4.62.3
Requires-Dist: xarray>=0.20.2
Requires-Dist: joblib>=1.2.0
Requires-Dist: pyarrow>=14.0.1
Requires-Dist: pydantic>=2.8.2
Provides-Extra: dev
Requires-Dist: pytest>=7.0.1; extra == "dev"
Requires-Dist: pytest-cov>=3.0.0; extra == "dev"
Requires-Dist: pytest-xdist>=2.5.0; extra == "dev"
Requires-Dist: pytest-clarity>=1.0.1; extra == "dev"
Requires-Dist: ruff<0.3.0,>=0.1.7; extra == "dev"
Requires-Dist: mypy<1.10.0,>=1.6.0; extra == "dev"
Requires-Dist: types-pyyaml>=6.0.12.12; extra == "dev"
Requires-Dist: types-requests>=2.31.0.9; extra == "dev"
Requires-Dist: pyfakefs>=5.3.0; extra == "dev"
Requires-Dist: requests-mock>=1.11.0; extra == "dev"
Requires-Dist: pre-commit>=3.0.0; extra == "dev"
Provides-Extra: docs
Requires-Dist: sphinx>=7.1.2; extra == "docs"
Requires-Dist: tomlkit>=0.12.0; extra == "docs"
Requires-Dist: sphinx-autodoc-typehints>=1.17.0; extra == "docs"
Requires-Dist: nbsphinx>=0.9.3; extra == "docs"
Requires-Dist: myst-parser>=2.0.0; extra == "docs"
Requires-Dist: pydata-sphinx-theme>=0.15.0; extra == "docs"
Provides-Extra: notebook
Requires-Dist: jupyter>=1.0.0; extra == "notebook"
Requires-Dist: ipykernel>=6.9.1; extra == "notebook"
Requires-Dist: jupyterlab>=4.0; extra == "notebook"
Requires-Dist: jupyterlab-h5web>=8.0.0; extra == "notebook"
Provides-Extra: all
Requires-Dist: sed-processor[dev,docs,notebook]; extra == "all"
Dynamic: license-file
